MANIFEST.in
README.md
requirements-dev.txt
requirements.txt
setup.py
src/ghwh/__init__.py
src/ghwh/app.py
src/ghwh/callbacks.py
src/ghwh/celery.py
src/ghwh/config.py
src/ghwh.egg-info/PKG-INFO
src/ghwh.egg-info/SOURCES.txt
src/ghwh.egg-info/dependency_links.txt
src/ghwh.egg-info/entry_points.txt
src/ghwh.egg-info/requires.txt
src/ghwh.egg-info/top_level.txt
src/ghwh/api/__init__.py
src/ghwh/api/utils.py
src/ghwh/api/webhook.py
src/ghwh_cli/__init__.py
src/ghwh_cli/send_event.py
src/ghwh_cli/simple_server.py
src/ghwh_data/__init__.py
src/ghwh_data/payloads/push.json.j2