Metadata-Version: 2.1
Name: ghwh
Version: 0.1.0
Summary: GitHub webhook handler app
Home-page: https://github.com/okomestudio/ghwh
Author: Taro Sato
License: UNKNOWN
Platform: Linux
Provides-Extra: dev
